onedict/__init__.py
onedict/merger.py
onedict/solvers.py
onedict-0.1.0.dist-info/LICENSE
onedict-0.1.0.dist-info/METADATA
onedict-0.1.0.dist-info/WHEEL
onedict-0.1.0.dist-info/RECORD
