Metadata-Version: 2.1
Name: onedict
Version: 0.1.0
Summary: A Python library for recursively merging dictionaries with customizable conflict resolution strategies.
Home-page: https://github.com/flusflas/onedict
License: MIT
Keywords: dictionaries,merge
Author: flusflas
Author-email: aflusflas@gmail.com
Requires-Python: >=3.9,<4.0
Classifier: License :: OSI Approved :: MIT License
Classifier: Operating System :: OS Independent
Classifier: Programming Language :: Python :: 3
Classifier: Programming Language :: Python :: 3.9
Classifier: Programming Language :: Python :: 3.10
Classifier: Programming Language :: Python :: 3.11
Classifier: Topic :: Utilities
Project-URL: Repository, https://github.com/flusflas/onedict
